uplevel/__init__.py
uplevel-0.0.5.dist-info/METADATA
uplevel-0.0.5.dist-info/WHEEL
uplevel-0.0.5.dist-info/top_level.txt
uplevel-0.0.5.dist-info/RECORD
